{"post_title":"","guid":"https:\/\/livewp.site\/wp\/md\/ewebot\/uiux-design\/","post_author":"","post_content":"","post_excerpt":"","post_id":18544,"pubDate":"Mon, 25 Nov 2024 10:45:13 +0000","post_date":"2024-11-25 10:45:13","post_date_gmt":"2024-11-25 10:45:13","comment_status":"closed","ping_status":"closed","post_name":"uiux-design","status":"inherit","post_parent":0,"menu_order":0,"post_type":"attachment","post_password":"","is_sticky":0,"terms":[],"postmeta":[{"meta_key":"_wp_attached_file","meta_value":"2024\/11\/uiux-design.jpg"},{"meta_key":"_wp_attachment_metadata","meta_value":"a:6:{s:5:\"width\";i:662;s:6:\"height\";i:464;s:4:\"file\";s:23:\"2024\/11\/uiux-design.jpg\";s:8:\"filesize\";i:70162;s:5:\"sizes\";a:8:{s:6:\"medium\";a:5:{s:4:\"file\";s:23:\"uiux-design-300x210.jpg\";s:5:\"width\";i:300;s:6:\"height\";i:210;s:9:\"mime-type\";s:10:\"image\/jpeg\";s:8:\"filesize\";i:17635;}s:9:\"thumbnail\";a:5:{s:4:\"file\";s:23:\"uiux-design-150x150.jpg\";s:5:\"width\";i:150;s:6:\"height\";i:150;s:9:\"mime-type\";s:10:\"image\/jpeg\";s:8:\"filesize\";i:10897;}s:15:\"gt3theme_mobile\";a:5:{s:4:\"file\";s:23:\"uiux-design-480x336.jpg\";s:5:\"width\";i:480;s:6:\"height\";i:336;s:9:\"mime-type\";s:10:\"image\/jpeg\";s:8:\"filesize\";i:31474;}s:21:\"woocommerce_thumbnail\";a:6:{s:4:\"file\";s:23:\"uiux-design-300x300.jpg\";s:5:\"width\";i:300;s:6:\"height\";i:300;s:9:\"mime-type\";s:10:\"image\/jpeg\";s:8:\"filesize\";i:24497;s:9:\"uncropped\";b:0;}s:29:\"woocommerce_gallery_thumbnail\";a:5:{s:4:\"file\";s:23:\"uiux-design-400x400.jpg\";s:5:\"width\";i:400;s:6:\"height\";i:400;s:9:\"mime-type\";s:10:\"image\/jpeg\";s:8:\"filesize\";i:34215;}s:29:\"variation_swatches_image_size\";a:5:{s:4:\"file\";s:21:\"uiux-design-50x50.jpg\";s:5:\"width\";i:50;s:6:\"height\";i:50;s:9:\"mime-type\";s:10:\"image\/jpeg\";s:8:\"filesize\";i:4826;}s:31:\"variation_swatches_tooltip_size\";a:5:{s:4:\"file\";s:23:\"uiux-design-100x100.jpg\";s:5:\"width\";i:100;s:6:\"height\";i:100;s:9:\"mime-type\";s:10:\"image\/jpeg\";s:8:\"filesize\";i:7430;}s:21:\"quick_view_image_size\";a:5:{s:4:\"file\";s:23:\"uiux-design-450x464.jpg\";s:5:\"width\";i:450;s:6:\"height\";i:464;s:9:\"mime-type\";s:10:\"image\/jpeg\";s:8:\"filesize\";i:42786;}}s:10:\"image_meta\";a:12:{s:8:\"aperture\";s:1:\"0\";s:6:\"credit\";s:0:\"\";s:6:\"camera\";s:0:\"\";s:7:\"caption\";s:0:\"\";s:17:\"created_timestamp\";s:1:\"0\";s:9:\"copyright\";s:0:\"\";s:12:\"focal_length\";s:1:\"0\";s:3:\"iso\";s:1:\"0\";s:13:\"shutter_speed\";s:1:\"0\";s:5:\"title\";s:0:\"\";s:11:\"orientation\";s:1:\"0\";s:8:\"keywords\";a:0:{}}}"},{"meta_key":"_emr_replace_author","meta_value":"1"},{"meta_key":"_edit_lock","meta_value":"1732555815:1"}],"comments":[],"media":[],"attachment_url":"https:\/\/livewp.site\/wp\/md\/ewebot\/wp-content\/uploads\/sites\/64\/2024\/11\/uiux-design.jpg"}